pixivFollowUpdateBot/__init__.py
pixivFollowUpdateBot/__main__.py
pixivFollowUpdateBot/bot.py
pixivFollowUpdateBot/followUpdates.py
pixivFollowUpdateBot/user_config.py
pixivFollowUpdateBot/utils.py
pfub-0.0.2.dist-info/METADATA
pfub-0.0.2.dist-info/WHEEL
pfub-0.0.2.dist-info/top_level.txt
pfub-0.0.2.dist-info/RECORD
